ase_quantumespresso/__init__.py
ase_quantumespresso/dos.py
ase_quantumespresso/espresso.py
ase_quantumespresso/ld1.py
ase_quantumespresso/namelist.py
ase_quantumespresso/pp.py
ase_quantumespresso/projwfc.py
ase_quantumespresso-0.0.4.dist-info/WHEEL
ase_quantumespresso-0.0.4.dist-info/METADATA
ase_quantumespresso-0.0.4.dist-info/RECORD
